virtue/.nfs00000000d8e7289e008e14ae
virtue/ConfigUtility.py
virtue/Geo.ils
virtue/GeoPoints.ils
virtue/HdbConfig.ils
virtue/LibUtility.py
virtue/MaeExport.ils
virtue/MaeMaestro.ils
virtue/SchUtility.py
virtue/Skillbridge.ils
virtue/Toml.ils
virtue/__init__.py
virtue/cdslib.py
virtue/cli.py
virtue/pyproject.toml
virtue/skillbridge.py
virtue/virtue.cdsLibMgr.il
virtue/virtue.cdsinit.ils
virtue/build/build_context.csh
virtue/build/build_context.il
virtue/build/virtue.init-build.ils
virtue/data_types/Dpl.ils
virtue/data_types/Lcv.ils
virtue/data_types/List.ils
virtue/data_types/Path.ils
virtue/data_types/Str.ils
virtue/plugins/__init__.py
virtue/plugins/hookspecs.py
virtue/plugins/lib.py
virtue/plugins/plugin_manager.py
virtue/skill_environment/__init__.py
virtue/skill_environment/api.py
virtue/skill_environment/cli.py
virtue/skill_environment/init_scripts.py
virtue/skill_package/Module.ils
virtue/skill_package/Package.ils
virtue/skill_package/__init__.py
virtue/skill_package/metadata.py
virtue/skill_package/metadata_data.py
virtue/test/Test.ils
virtue/test/TestFile.ils
virtue/test/TestFixtures.ils
virtue/test/TestFunction.ils
virtue/test/TestSuite.ils
virtue/virtue_dev_work/README.md
virtue_skill-0.4.1.dist-info/entry_points.txt
virtue_skill-0.4.1.dist-info/LICENSE
virtue_skill-0.4.1.dist-info/WHEEL
virtue_skill-0.4.1.dist-info/METADATA
virtue_skill-0.4.1.dist-info/RECORD
