Metadata-Version: 2.1
Name: virtue-skill
Version: 0.4.1
Summary: Cadence Virtuoso SKILL and Python library
Keywords: circuit design,design automation,Cadence,virtuoso,SKILL,Python
Author-email: Curtis Mayberry <Curtisma3@gmail.com>
Maintainer-email: Curtis Mayberry <Curtisma3@gmail.com>
Requires-Python: >=3.7
Classifier: Topic :: Scientific/Engineering :: Electronic Design Automation (EDA)
Classifier: Topic :: Scientific/Engineering
Classifier: Programming Language :: Python :: 3 :: Only
Classifier: Programming Language :: Python :: 3.8
Classifier: Programming Language :: Python :: 3.9
Classifier: Programming Language :: Python :: 3.10
Classifier: Programming Language :: Other Scripting Engines
Classifier: Programming Language :: Other
Classifier: License :: OSI Approved :: MIT License
Classifier: Operating System :: POSIX :: Linux
Classifier: Topic :: Software Development
Classifier: Topic :: Software Development :: Libraries
Classifier: Topic :: Software Development :: Libraries :: Python Modules
Classifier: Topic :: Software Development :: Testing
Classifier: Topic :: Software Development :: Testing :: Unit
Requires-Dist: typer >= 0.6.1, < 1.0.0
Requires-Dist: rich >= 12.5.1, < 13.0.0
Requires-Dist: pluggy >= 1.0.0, < 2.0.0
Requires-Dist: pre-commit == 2.20.0 ; extra == "dev"
Requires-Dist: sphinx == 4.5.0 ; extra == "doc"
Requires-Dist: pydata-sphinx-theme == 0.9.0 ; extra == "doc"
Requires-Dist: sphinx-panels == 0.6.0 ; extra == "doc"
Requires-Dist: sphinx_copybutton == 0.5.0 ; extra == "doc"
Requires-Dist: sphinx-autobuild == 2021.3.14 ; extra == "doc"
Requires-Dist: sphinx-github-changelog == 1.2.0 ; extra == "doc"
Requires-Dist: sphinx-sitemap == 2.2.0 ; extra == "doc"
Requires-Dist: sphinx-click == 4.3.0 ; extra == "doc"
Requires-Dist: softworks ; extra == "optional"
Requires-Dist: skillbridge ; extra == "optional"
Requires-Dist: pytest >=7.1.2 ; extra == "test"
Requires-Dist: pylint >= 2.14.4 ; extra == "test"
Requires-Dist: mypy >= 0.961 ; extra == "test"
Project-URL: Documentation, http://www.cascode-labs.org/virtue/
Project-URL: Home, http://www.cascode-labs.org/virtue/
Project-URL: Source, https://github.com/cascode-labs/virtue
Provides-Extra: dev
Provides-Extra: doc
Provides-Extra: optional
Provides-Extra: test
